navertts/__init__.py
navertts/cli.py
navertts/constants.py
navertts/lang.py
navertts/tts.py
navertts/utils.py
navertts/version.py
navertts/tests/__init__.py
navertts/tests/test_cli.py
navertts/tests/test_lang.py
navertts/tests/test_tts.py
navertts/tests/test_utils.py
navertts/tokenizer/__init__.py
navertts/tokenizer/core.py
navertts/tokenizer/pre_processors.py
navertts/tokenizer/symbols.py
navertts/tokenizer/tokenizer_cases.py
NaverTTS-0.3.1.dist-info/LICENSE
NaverTTS-0.3.1.dist-info/METADATA
NaverTTS-0.3.1.dist-info/WHEEL
NaverTTS-0.3.1.dist-info/entry_points.txt
NaverTTS-0.3.1.dist-info/top_level.txt
NaverTTS-0.3.1.dist-info/RECORD
