Metadata-Version: 2.1
Name: NaverTTS
Version: 0.3.1
Summary: NaverTTS (NAVER Text-to-Speech), a Python library and CLI tool to interface with NAVER Papago text-to-speech API
Home-page: https://github.com/scottgigante/NaverTTS
Author: Scott Gigante
Author-email: scottgigante@gmail.com
License: MIT
Keywords: navertts,text to speech,NAVER Papago,TTS
Classifier: Environment :: Console
Classifier: Intended Audience :: Developers
Classifier: License :: OSI Approved :: MIT License
Classifier: Operating System :: MacOS
Classifier: Operating System :: Unix
Classifier: Operating System :: POSIX
Classifier: Operating System :: POSIX :: Linux
Classifier: Operating System :: Microsoft :: Windows
Classifier: Programming Language :: Python :: 3.5
Classifier: Programming Language :: Python :: 3.6
Classifier: Programming Language :: Python :: 3.7
Classifier: Programming Language :: Python :: 3.8
Classifier: Topic :: Software Development :: Libraries
Classifier: Topic :: Multimedia :: Sound/Audio :: Speech
Requires-Python: >= 3.5
License-File: LICENSE
Requires-Dist: six
Requires-Dist: beautifulsoup4
Requires-Dist: click
Requires-Dist: requests
Provides-Extra: test
Requires-Dist: pytest (>=4.6) ; extra == 'test'
Requires-Dist: pytest-cov ; extra == 'test'
Requires-Dist: flake8 ; extra == 'test'
Requires-Dist: testfixtures ; extra == 'test'
Requires-Dist: mock ; extra == 'test'
Requires-Dist: coveralls ; extra == 'test'
